pyattackforge/__init__.py
pyattackforge/client.py
pyattackforge/prev_client.py
pyattackforge-0.1.9.dist-info/licenses/LICENSE
pyattackforge-0.1.9.dist-info/METADATA
pyattackforge-0.1.9.dist-info/WHEEL
pyattackforge-0.1.9.dist-info/top_level.txt
pyattackforge-0.1.9.dist-info/RECORD
